fds/__init__.py
fds/sdk/__init__.py
fds/sdk/EventCalendar/__init__.py
fds/sdk/EventCalendar/api_client.py
fds/sdk/EventCalendar/configuration.py
fds/sdk/EventCalendar/exceptions.py
fds/sdk/EventCalendar/model_utils.py
fds/sdk/EventCalendar/rest.py
fds/sdk/EventCalendar/api/__init__.py
fds/sdk/EventCalendar/api/company_api.py
fds/sdk/EventCalendar/apis/__init__.py
fds/sdk/EventCalendar/model/__init__.py
fds/sdk/EventCalendar/model/company_event_request.py
fds/sdk/EventCalendar/model/company_event_request_data.py
fds/sdk/EventCalendar/model/company_event_request_data_date_time.py
fds/sdk/EventCalendar/model/company_event_request_data_universe.py
fds/sdk/EventCalendar/model/company_event_response.py
fds/sdk/EventCalendar/model/company_event_response_data.py
fds/sdk/EventCalendar/model/error.py
fds/sdk/EventCalendar/model/error_response.py
fds/sdk/EventCalendar/models/__init__.py
fds.sdk.EventCalendar-0.21.1.dist-info/LICENSE
fds.sdk.EventCalendar-0.21.1.dist-info/METADATA
fds.sdk.EventCalendar-0.21.1.dist-info/WHEEL
fds.sdk.EventCalendar-0.21.1.dist-info/top_level.txt
fds.sdk.EventCalendar-0.21.1.dist-info/RECORD
